pyqtgraph_extended/__init__.py
pyqtgraph_extended/opengl/__init__.py
pyqtgraph_extensions/__init__.py
pyqtgraph_extensions/AlignedPlot.py
pyqtgraph_extensions/autorange_toggle_off.png
pyqtgraph_extensions/autorange_toggle_off.svg
pyqtgraph_extensions/autorange_toggle_on.png
pyqtgraph_extensions/autorange_toggle_on.svg
pyqtgraph_extensions/AxisItem.py
pyqtgraph_extensions/ellipsis.png
pyqtgraph_extensions/ellipsis.svg
pyqtgraph_extensions/examples/demo_axis_alignment.py
pyqtgraph_extensions/examples/demo_color_bar.py
pyqtgraph_extensions/examples/demo_misc.py
pyqtgraph_extensions/examples/demo_right_top_axes.py
pyqtgraph_extensions/functions.py
pyqtgraph_extensions/GraphicsLayout.py
pyqtgraph_extensions/hook-pyqtgraph_extensions.py
pyqtgraph_extensions/misc.py
pyqtgraph_extensions/offcuts.py
pyqtgraph_extensions/opengl/__init__.py
pyqtgraph_extensions/opengl/test/test_pyqtgraph_extensions_opengl.py
pyqtgraph_extensions/test/test_all.py
pyqtgraph_extensions/test/test_functions.py
pyqtgraph_extensions/test/test_ImageItem.py
pyqtgraph_extensions/test/try_deleting.py
pyqtgraph_recipes/__init__.py
pyqtgraph_recipes/jet_white.txt
pyqtgraph_recipes/jet_white_clip.txt
pyqtgraph_recipes/parula.txt
pyqtgraph_recipes/parula_white.txt
pyqtgraph_recipes/pyqtgraph_recipes.py
pyqtgraph_recipes/test/test_recipes.py
pyqtgraph_extensions-0.5.9.dist-info/entry_points.txt
pyqtgraph_extensions-0.5.9.dist-info/LICENSE.txt
pyqtgraph_extensions-0.5.9.dist-info/WHEEL
pyqtgraph_extensions-0.5.9.dist-info/METADATA
pyqtgraph_extensions-0.5.9.dist-info/RECORD
