Metadata-Version: 2.1
Name: pyqtgraph-extensions
Version: 0.5.9
Summary: Various extensions for pyqtgraph.
Home-page: https://github.com/draustin/pyqtgraph_extensions
License: MIT
Author: Dane Austin
Author-email: dane_austin@fastmail.com.au
Requires-Python: >=3.8,<4.0
Classifier: License :: OSI Approved :: MIT License
Classifier: Programming Language :: Python :: 3
Classifier: Programming Language :: Python :: 3.8
Classifier: Programming Language :: Python :: 3.9
Classifier: Programming Language :: Python :: 3.10
Requires-Dist: PyQt5 (>=5.14.2,<6.0.0)
Requires-Dist: mathx (>=0.2.1)
Requires-Dist: pyopengl (>=3.1.5,<4.0.0)
Requires-Dist: pyqtgraph (>=0.11)
Project-URL: Repository, https://github.com/draustin/pyqtgraph_extensions
